<?xml version="1.0" encoding="UTF-8"?>
<config date="1345046972103" transient="false" version="3.0">
<site enabled="true" policy="USER-EXCLUDE" updateable="true" url="platform:/base/">
<feature id="org.eclipse.birt.chart" url="features/org.eclipse.birt.chart_3.7.1.v20110905-7r9e7DFQCnvKN75--lXE5/" version="3.7.1.v20110905-7r9e7DFQCnvKN75--lXE5">
</feature>
<feature id="org.eclipse.birt.crosstab" url="features/org.eclipse.birt.crosstab_2.3.1.v20080630-4518s733I3K3C/" version="2.3.1.v20080630-4518s733I3K3C">
</feature>
<feature id="org.apache.commons.codec" url="features/org.apache.commons.codec_1.3.0.v20070920-12-7w3119164102711/" version="1.3.0.v20070920-12-7w3119164102711">
</feature>
<feature id="org.eclipse.birt" url="features/org.eclipse.birt_3.7.1.v20110905-BDF9E8OGTzuHfoz-Au7-CWvXDn6N/" version="3.7.1.v20110905-BDF9E8OGTzuHfoz-Au7-CWvXDn6N">
</feature>
<feature id="org.eclipse.birt.osgi.runtime.sdk" url="features/org.eclipse.birt.osgi.runtime.sdk_3.7.0.v20110905-777D186vH9ByS6g9QJbm7yp7gZp-/" version="3.7.0.v20110905-777D186vH9ByS6g9QJbm7yp7gZp-">
</feature>
<feature id="org.eclipse.birt.chart.integration.wtp" plugin-identifier="org.eclipse.birt.chart.integration.wtp.ui" url="features/org.eclipse.birt.chart.integration.wtp_2.3.1.v20080630-2207w31191842/" version="2.3.1.v20080630-2207w31191842">
</feature>
<feature id="org.eclipse.birt.report.designer" url="features/org.eclipse.birt.report.designer_2.3.1.v20080630-7X7n7FECLqlyX1jw48bOyH4E0ha5/" version="2.3.1.v20080630-7X7n7FECLqlyX1jw48bOyH4E0ha5">
</feature>
<feature id="com.lowagie.itext" url="features/com.lowagie.itext_1.5.4.v20080225-1437w31191339/" version="1.5.4.v20080225-1437w31191339">
</feature>
<feature id="org.apache.derby.core" url="features/org.apache.derby.core_10.3.1.4/" version="10.3.1.4">
</feature>
<feature id="org.eclipse.birt.report.designer.debug" url="features/org.eclipse.birt.report.designer.debug_2.3.1.v20080630-4518s733I3K49/" version="2.3.1.v20080630-4518s733I3K49">
</feature>
<feature id="org.eclipse.birt.osgi.runtime" url="features/org.eclipse.birt.osgi.runtime_3.7.1.v20110905-9qE57vG3Z7DSLdz0X15PZX/" version="3.7.1.v20110905-9qE57vG3Z7DSLdz0X15PZX">
</feature>
<feature id="org.w3c.sac" url="features/org.w3c.sac_1.3.0.v20080102-46-_kE77b7U_N56BA/" version="1.3.0.v20080102-46-_kE77b7U_N56BA">
</feature>
<feature id="org.eclipse.birt.report.data.oda.jdbc.dbprofile.sqlbuilder.feature" url="features/org.eclipse.birt.report.data.oda.jdbc.dbprofile.sqlbuilder.feature_2.3.1.v20080630-787A39xxELbRjZxlz-xBh6S1fcsX/" version="2.3.1.v20080630-787A39xxELbRjZxlz-xBh6S1fcsX">
</feature>
<feature id="org.eclipse.birt.chart.osgi.runtime" url="features/org.eclipse.birt.chart.osgi.runtime_3.7.0.v20110905-80AC7JFYeMBkfQxLF3Pbd/" version="3.7.0.v20110905-80AC7JFYeMBkfQxLF3Pbd">
</feature>
<feature id="org.eclipse.birt.chart.osgi.runtime.sdk" url="features/org.eclipse.birt.chart.osgi.runtime.sdk_3.7.1.v20110905-777D-855DGBMRamOMnsf5gXe4z0r/" version="3.7.1.v20110905-777D-855DGBMRamOMnsf5gXe4z0r">
</feature>
<feature id="org.eclipse.birt.report.runtime" url="features/org.eclipse.birt.report.runtime_2.3.1.v200807162-7k8E7KEMVkywAg5R0ebrWS/" version="2.3.1.v200807162-7k8E7KEMVkywAg5R0ebrWS">
</feature>
<feature id="org.eclipse.birt.cshelp" url="features/org.eclipse.birt.cshelp_3.7.1.v20110905-4607w31221A16/" version="3.7.1.v20110905-4607w31221A16">
</feature>
<feature id="org.mozilla.rhino" url="features/org.mozilla.rhino_1.6.7.v20071217-1567w31191325/" version="1.6.7.v20071217-1567w31191325">
</feature>
<feature id="org.eclipse.birt.chart.runtime" url="features/org.eclipse.birt.chart.runtime_2.3.1.v20080630-7X8n6EMNbos-rAPIYtmR1/" version="2.3.1.v20080630-7X8n6EMNbos-rAPIYtmR1">
</feature>
<feature id="org.eclipse.birt.report.designer.editor.xml.wtp" plugin-identifier="org.eclipse.birt.report.designer.ui.editor.xml.wtp" url="features/org.eclipse.birt.report.designer.editor.xml.wtp_3.7.1.v20110905-809u7NFT0z0-TWCm5MjN7w/" version="3.7.1.v20110905-809u7NFT0z0-TWCm5MjN7w">
</feature>
<feature id="org.eclipse.birt.chart.doc.isv" url="features/org.eclipse.birt.chart.doc.isv_3.7.1.v20110905-4607w31221A16/" version="3.7.1.v20110905-4607w31221A16">
</feature>
<feature id="org.eclipse.birt.chart.cshelp" url="features/org.eclipse.birt.chart.cshelp_3.7.1.v20110905-4607w31221A16/" version="3.7.1.v20110905-4607w31221A16">
</feature>
<feature id="org.eclipse.birt.report.data.oda.jdbc.dbprofile.feature" url="features/org.eclipse.birt.report.data.oda.jdbc.dbprofile.feature_2.3.1.v200807162-67829oA55S5SAP/" version="2.3.1.v200807162-67829oA55S5SAP">
</feature>
<feature id="org.eclipse.birt.doc.isv" url="features/org.eclipse.birt.doc.isv_3.7.1.v20110905-4607w31221A16/" version="3.7.1.v20110905-4607w31221A16">
</feature>
<feature id="org.eclipse.birt.example" url="features/org.eclipse.birt.example_3.7.1.v20110905-7M7l6DZRDKKEBDl/" version="3.7.1.v20110905-7M7l6DZRDKKEBDl">
</feature>
<feature id="org.eclipse.birt.doc" url="features/org.eclipse.birt.doc_3.7.1.v20110905-4607w31221A16/" version="3.7.1.v20110905-4607w31221A16">
</feature>
</site>
</config>
